Metadata-Version: 2.1
Name: TrackerAssist
Version: 0.1.4
Summary: TrackerAsisst is a Python library for interacting with Request Tracker's REST API 2.0 (pre-installed as of RT 5.0.0).
Home-page: https://github.com/tyler-tee/trackerassist
Author: Tyler Talaga
Author-email: ttalaga@wgu.edu
License: GPLv3
Platform: UNKNOWN
